Metadata-Version: 1.1
Name: giphypy
Version: 0.0.2
Summary: Python Wrapper for Giphy API
Home-page: https://github.com/The-PyWaiters/GiphyPy
Author: The PyWaiters
Author-email: freshjelly12@yahoo.com
License: MIT
Keywords: web,api,giphy,wrapper
Platform: UNKNOWN
Classifier: Development Status :: 1 - Planning
Classifier: Environment :: Web Environment
Classifier: Programming Language :: Python :: 3.6
Classifier: License :: OSI Approved :: MIT License
